rest_framework_tus/__init__.py
rest_framework_tus/apps.py
rest_framework_tus/constants.py
rest_framework_tus/exceptions.py
rest_framework_tus/middleware.py
rest_framework_tus/models.py
rest_framework_tus/parsers.py
rest_framework_tus/receivers.py
rest_framework_tus/routers.py
rest_framework_tus/serializers.py
rest_framework_tus/settings.py
rest_framework_tus/signals.py
rest_framework_tus/states.py
rest_framework_tus/storage.py
rest_framework_tus/urls.py
rest_framework_tus/utils.py
rest_framework_tus/views.py
rest_framework_tus/migrations/0001_initial.py
rest_framework_tus/migrations/0002_auto_20170406_0620.py
rest_framework_tus/migrations/0003_auto_20170619_0358.py
rest_framework_tus/migrations/0004_auto_20200317_1002.py
rest_framework_tus/migrations/0005_alter_upload_upload_length.py
rest_framework_tus/migrations/__init__.py
rest_framework_tus/static/css/rest_framework_tus.css
rest_framework_tus/static/js/rest_framework_tus.js
rest_framework_tus/templates/rest_framework_tus/base.html
leukeleu_drf_tus-2.0.0.dist-info/LICENSE
leukeleu_drf_tus-2.0.0.dist-info/METADATA
leukeleu_drf_tus-2.0.0.dist-info/WHEEL
leukeleu_drf_tus-2.0.0.dist-info/top_level.txt
leukeleu_drf_tus-2.0.0.dist-info/RECORD
