Metadata-Version: 2.1
Name: leukeleu-drf-tus
Version: 2.0.0
Summary: A Tus (tus.io) library for Django Rest Framework
Home-page: https://github.com/leukeleu/leukeleu-drf-tus
Author: Leukeleu
Author-email: info@leukeleu.nl
License: MIT
Keywords: drf-tus
Classifier: Development Status :: 5 - Production/Stable
Classifier: Framework :: Django
Classifier: Framework :: Django :: 3.2
Classifier: Framework :: Django :: 4.2
Classifier: Intended Audience :: Developers
Classifier: License :: OSI Approved :: MIT License
Classifier: Natural Language :: English
Classifier: Programming Language :: Python :: 3.8
Classifier: Programming Language :: Python :: 3.9
Classifier: Programming Language :: Python :: 3.10
Classifier: Topic :: Software Development :: Libraries :: Python Modules
License-File: LICENSE
Requires-Dist: Django (>=3.2.1)
Requires-Dist: djangorestframework (>=3.11.0)
Requires-Dist: jsonfield (>=2.0.0)
Requires-Dist: django-fsm (==2.7.1)
